cyDisp.cpython-311-darwin.so
dispCal/__init__.py
dispCal/disp.py
dispCal/dispV2.py
dispCal/setup.py
dispCal/test.py
dispCal-0.2.3.dist-info/LICENSE
dispCal-0.2.3.dist-info/METADATA
dispCal-0.2.3.dist-info/WHEEL
dispCal-0.2.3.dist-info/top_level.txt
dispCal-0.2.3.dist-info/RECORD
