Metadata-Version: 2.1
Name: dispCal
Version: 0.2.3
Summary: Calculate Surface Wave Dispersion
Home-page: https://github.com/baogegeJiang/dispCal
Author: baogege(Jiang Yiran)
Author-email: baogege@pku.edu.cn
Classifier: Programming Language :: Python :: 3
Classifier: Development Status :: 4 - Beta
Classifier: Environment :: Other Environment
Classifier: Intended Audience :: Developers
Classifier: Topic :: Software Development :: Libraries :: Python Modules
License-File: LICENSE
